LICENSE
README.md
setup.py
CircuitSAT.egg-info/PKG-INFO
CircuitSAT.egg-info/SOURCES.txt
CircuitSAT.egg-info/dependency_links.txt
CircuitSAT.egg-info/entry_points.txt
CircuitSAT.egg-info/requires.txt
CircuitSAT.egg-info/top_level.txt
circuitsat/CircuitSAT.py
circuitsat/CircuitSATLexer.py
circuitsat/CircuitSATListener.py
circuitsat/CircuitSATParser.py
circuitsat/CircuitSATVisitor.py
circuitsat/CircuitSAT_.py
circuitsat/_csat.py